girder_sentry/__init__.py
girder_sentry/rest.py
girder_sentry/settings.py
girder_sentry/web_client/dist/girder-plugin-sentry.umd.cjs
girder_sentry/web_client/dist/style.css
girder_sentry-5.0.0a14.dev27.dist-info/METADATA
girder_sentry-5.0.0a14.dev27.dist-info/WHEEL
girder_sentry-5.0.0a14.dev27.dist-info/entry_points.txt
girder_sentry-5.0.0a14.dev27.dist-info/top_level.txt
girder_sentry-5.0.0a14.dev27.dist-info/RECORD
