Metadata-Version: 2.4
Name: girder-sentry
Version: 5.0.0a14.dev27
Summary: Allow the automatic tracking of issues using Sentry.
Maintainer: Kitware, Inc.
Maintainer-email: kitware@kitware.com
License: Apache 2.0
Classifier: Development Status :: 5 - Production/Stable
Classifier: Environment :: Web Environment
Classifier: Operating System :: OS Independent
Classifier: Programming Language :: Python
Classifier: Programming Language :: Python :: 3
Requires-Python: >=3.10
Requires-Dist: girder>=3
Requires-Dist: sentry-sdk
Dynamic: classifier
Dynamic: license
Dynamic: maintainer
Dynamic: maintainer-email
Dynamic: requires-dist
Dynamic: requires-python
Dynamic: summary
